[
  {
    "field_type": "input_code",
    "default_value": null,
    "field_key": "code",
    "field_title": "Code",
    "data_type": "string",
    "required": true,
    "hidden": false,
    "meta_data": {
      "language": "Python"
    },
    "order": 0
  },
  {
    "field_type": "input_schema_editor",
    "default_value": null,
    "field_key": "output_schema",
    "field_title": "Output schema",
    "data_type": "json",
    "required": true,
    "hidden": false,
    "meta_data": {
      "language": "json"
    },
    "order": 1
  },
  {
    "field_type": "input_keyvalue",
    "default_value": null,
    "field_key": "function_inputs_config",
    "field_title": "Input Names Config",
    "data_type": "json",
    "required": false,
    "hidden": false,
    "meta_data": null,
    "order": 2
  }
]